Metadata-Version: 1.0
Name: very-fantastic-ascii
Version: 1.0.0
Summary: Very Fantastic ASCII
Home-page: UNKNOWN
Author: Matt
Author-email: example@example.com
License: MIT
Platform: UNKNOWN
